{"id":3,"sides":[["ש","פ","ב"],["ו","מ","נ"],["ל","י","ע"]],"optimal":2,"solution":["ענפים","משולב"],"words":["של","עם","יש","בין","לפני","לו","שם","בו","מי","בן","שלו","שנים","לפי","שיש","בני","פי","פעם","לב","שוב","ימים","נשים","מים","עושים","עולם","פנים","ים","פעמים","לבן","ימי","מבין","למען","שלוש","פני","מפני","מיני","לוי","מין","שמש","עשוי","בי","שישי","לשים","שלב","יופי","ישובים","לבני","שלם","עשו","נשמע","בנימין","בניו","שי","עוף","פלפל","מבינים","שמע","שמים","שמי","ישן","מבני","משמש","ימין","יפים","מבנים","משני","בישול","בנים","פנימי","עמי","שימש","מעשי","פניו","ישי","יפני","נפל","ישנים","פול","ענף","יפן","ישוב","משלו","יניב","מפי","עולמי","משלמים","משלב","משל","משולב","משלם","לפניו","נשוי","יו","פעמי","מימי","שלבים","משמע","ביבי","שלושים","לבוש","שים","שלמים","נעמי","פן","בול","לפנים","נע","מעשים","שעם","נעשו","שלבי","משוב","משמשים","ביוב","עשן","לבו","פופ","פיו","ישלם","נענע","מינים","ישוע","מעשיו","בל","מפעם","ישו","שמעו","ענבל","ענפים","בוש","משנים","וי","נפלו","בלבול","עמים","יבין","שלפי","משולש","משיב","נעשים","ניב","ענבים","משעשע","לבי","שושן","עמל","נשי","בלו","ימיו","שן","נעם","משי","ביני","שישים","עני","בושם","ענפי","משולבים","שיני","מעשן","ישמש","עול","נבו","עובי","שמפו","פיני","נשמעו","משלבים","שימי","שימשו","שלש","ולשים","שובו","לובי","פניני","משולם","מיפוי","ישמע","מפנים","שולם","ישולם","שמיני","מען","פולני","מבושל","נבין","מעוף","נשען","שיבוש","מעשנים","בם","לבם","שלפיו","ישים","בלם","לוב","מבולבל","מיושן","מעושן","ין","מל","מבלבל","פין","נבע","עף","עב","נעול","ישמשו","לבושים","פנינים","מש","שלף","מפל","משמעו"]}