{"id":59,"sides":[["א","ת","מ"],["ל","ש","י"],["ו","ק","ה"]],"optimal":2,"solution":["השאלות","תיקים"],"words":["לא","או","מה","היא","היה","הם","אל","לו","אותו","שם","יום","מי","היום","אלא","היו","אותה","תל","להם","לה","יהיה","אלה","למה","אותי","אלו","קשה","מול","ימים","אי","שום","שאלות","מהם","מים","שתי","אולם","משה","מלא","תהיה","ים","קל","שקל","שאלה","ימי","יהיו","השם","לאומי","לוי","השאלה","שמש","תיק","שמות","שמו","קלה","הלא","איתי","אש","שמואל","משקל","תלוי","שמה","מהי","השמש","קיום","אשתו","שאל","הלאה","שמים","שמי","תום","משמש","השאלות","אות","קשות","שאול","אשה","לאומית","מותו","היות","יומי","שאי","שמלות","לאו","מלאו","מלאים","קלות","שואל","תלת","תיקים","תה","אותיות","לאותו","שאלתי","לאי","תלויה","משא","מלוא","אשת","תשתית","שאלו","שואה","מלאי","תשתיות","אולמות","שאלת","מיקי","איום","לאה","משקאות","מות","שמלה","משק","יו","קיומו","מימי","תהיו","אלול","קם","תקלה","מקל","אהיה","תיקי","שמלת","משתלם","תקלות","הא","יומית","אוי","היותו","השתלמות","ימות","מימוש","קיומה","יהלומים","לאותה","יואל","משמשת","אימה","השמות","ותיק","קמה","אשם","אשתי","מקש","ותיקים","תהא","יהי","השתלת","יהא","מלאות","משתי","איומים","יהלום","משתלמים","תיאום","שואלת","אימות","שקיות","השקת","תו","שקית","משאית","אשמה","וי","תשואה","מותק","יומיומי","שה","תלות","איה","מותה","תשאלו","התל","השתלות","מיה","אומות","ימיו","משאיות","מולו","שותה","לאומיות","היותה","שק","הל","תות","שומשום","השמה","ותק","אום","האשמה","קי","מקשה","תותים","ימית","שותים","הלם","התקלה","אותות","אלמלא","לאות","מקלות","משאלות","משולם","תלויות","שומה","תשומות","אומה","שולם","קש","מלה","קמו","מושא","שתים","מולם","אימי","שולמית","לאום","שמשה","אשמים","יומו","השתלמויות","יומיומית","הלוא","תשאל","מולה","השקיה","יואש","יומיות","משקי","משמשות","מקים","לולא","מל","המה","האשמות","קמים","שולמו","תשואות","משומש","משאל","שתל","מקימים","מום","האשם","אהל","יתומים","מש","יתום","שקמה","הלה","קת","איומה","שולה","קלוי","שמותיהם","משמים","קיומי","משו","המום","ימימה","תלוש","משקלו","מואשם","שוש","שתו","קלוש","תהיות","מיתה","שתה","ימלא","התקשה","איומי","תהיתי","תשמש","מימיו","התקלות","תלמי","הלום","משאלה","השקית","ימיה","קשתות","השתל","מקלה","קיו","מיהם","מקימה","אלת","תלמה","ותיקי","לולו","תהי","שא","יקל","תולה","שותק","ימותו","יתקשה","שקם","ימלאו","מומים","יאוש","לול","התקשו","המומים","מוש","תיקיות","המות","יומיומיות","היותי","אימים","קיומית","איתות","שאו","שקי","משתה","יומה","השתלה","לאומה","משתלמות","שהתה","לולה","המי","תקים","יושק","מיושם","מהל","השהיה","אשאל","תלולה","התקשתה","תלול","שולמה","שקים","משקים","משאלת","יקשה","מקימי","יקים","השתלם","שתיתי","השקיות","משוא","שהיתי","קלו","תלו","שהי","תשולם","מושם","תלאות","המומה","תלה","מיו","שותקים","שקמו","משקלה","קימל","יתקשו","שקלו","ימה","קיק","מומו","שקלתי","השמשות","התקלקל","שמשות","יושם","שתק","יהלומי","השק","קיא","תש","שקלול","ימיות","אלוש","השאלת","שומות","משתלה","אולמי","השקתו","משקלם","מותי","שאלתיאל","קיאקים","שת","תיקיה","אשא","שמימי","ויולה","מיואש","יומיום","לאומים","שותקת","האשמים","משותק","לולאה","תשאול","מומי","תקל","משאות","משול","אותותיו","תותי","איות","מלמל","משומשות","לולאות","השתק","משולמים","יתוש","ימיהם","שקמים","השמימה","יאה","אקמול","מותש","משואות","השמשה","יקימו","שתוי","שתיקת","תהל","מימש","שאלתו","שהיות","מיואשת","מואשמים","משקם","איומות","שומו","קלת","אלות","משתלת","שמשם","משתק","משושה","מותשת","אקים","יתומה","מלת","תומו","משומשת","שואלות","השאה","שאולה","תשתה","קימה","קיומיות","מיהי","אלם","שמיה","משתלות","קלושה","שתית","מימיה","לקתה","שול","הלקאה","שתלו","שמשו","תשתו","מימית","שקלה","תקלת","שתול","השתלמה","שתקתי","מיושמים","מקלקל","מקשת","יושמו","המולה","איתותים","מושק","קשתי","התשה","משולה","מולאו","המיתה","משותקת","קשקשת","תושק","תשוש","יקלו","מלמלה","האהל","איו","משהי","קמות","שמית","מהלומה","איוש","מלו","תקתק","אותותיה","מקשקש","יושמה","המו","מיתות","מולא","מומש","מהלומות","תהתה","מומשה","שמיות","יואשם","מקיא","מימשו","השקתה","קימות","מומשו","משקית","מושאי","מימושה","מימשה","משקמים","מקימות","שתיקתו","מלות","מושתל","מושתק","תלולות","מיושמות","שמלתה","מקשות","תלוית","שמימית","אלאה","הלמה","יאי","משתיק","מושתקים","שמשת","אימהית","המולת","תיאומים","תשקלו","מימושו","קשתית","תיושם","שתלה","מקם","תקשה","תיתקלו","מקמו","מושאל","מהתלות","מימיהם","שאלותיו","שמותיו","מלמלתי","היתקלות","התלהמות","משהים","הלאו","תשתלם","מלאית","יתקלקל","תלתה","אשמות","התש","מיקם","משתקת","יתלה","תומי","משותקים","הלמו","תומה","יתקל","קיאק","שקיק","מקיאה","משאלתו","השתקת","הלמות","אשתה","אותותיהם","תלושה","תיתקל","שושה","יתומי","יתקתק","התקשות","היקש","שותל","המומות","מיתי","מקלקלת","אימהי","התקלקלה","המיתי","ימול","שתום","מימיות","משולמות","המית","משאו","תלותי","יתקלו","תקלו","קתי","שותות","תלותו","הלומי","קמי","יקשו","תלותית","קלקל","מושקים","קשקש","משמימה","ימוש","מהתל","איתותי","איומיו","אשמו","שאלותיהם","קמל","תקיא","ימומש","מומיה","קלויה","יושת","מיקמו","תלתל","יקלקל","תשושה","משתיקים","משמימים","יתומות","מלק","תהית","שאולות","מלמול","שאלתה","התקלקלו","ימולאו","מיתית","מושקת","תקלקל","תקימו","תשתי","שושו","שתלתי","מולאה","קלויות","יתלו","מקשקשת","קלושות","השתיק","ימשול","תשו","קשתים","משתקים","משקיות","יאות","משתים","ימומשו","אומי","אומיה","שקלולם","מקלו","השתלמו","מומה","שתיקתה","האשמי","תלותה","לקי","קשתיות","מהלם","מושהים","יאשם","קלקלו","תויק","משאלותיו","מושתלת","מימושם","מימשתי","מיקמה","מומיות","שקיקי","ימולא","תותה","אושא","שקיקים","משקלות","איומו","השאלתי","קלקלה","יתקלקלו","תשתיתי","היתקלויות","התלם","מקיאים","שמימיות","השתקם","המיתו","שקלת","מקימיה","תיאומי","מושתקת","יואשמו","השאל","תשתקי","השתהתה","משקשקים","השקתי","משאלותיהם","משתקמים","ותקם","מקלם","תלותיות","אומים","משאלתה","אלמותי","תלושות","משתקם","קשתו","מושהית","תשת","משאי","שותי","תשומה","תואשם","שהית","מקימיו","השהיות","תלאותיו","שאלותיה","אקלה","השתקמה","משתיה","קלקלת","שותלת","מושה","שתויה","משמימות","אומו","השת","משאיתו","קיאו","מהמהם","יהלומה","משקשק","האשמותיו","מושאים","משאלתי","מלקים","יושתו","יקלקלו","מותשות","אותיותיו","אלמות","שולת","תשמשו","לאומיותו","קשתה","השתית","תיקיו","אולמה","המהם","שתות","תלאותיה","משתהים","לקיתי","מיקשה","יושאל","יהלמו","קתות","ימקם","היקשה","משמשו","אקשה","שומי","תשתיתית","מיתיות","איומיה","משת","אשקל","אקל","מושאלת","אלמותית","תיאות","מלואי","משתית","הלאים","אשו","שתקת","מלאיה","שמלתי","מהתלה","תקשו","האהלה","תיקיהם","קשקשו","יאשמו","השמשת","שואות","קיאה","ימושו","השאלתו","השהתה","מושת","לקית","הלומים","תומים","לוש","תולות","המיה","היתל","היתול","הלאימה","שמותיה","מלמלו","משתיקי","לושו","אולמו","מושמים","יאש","שמשתי","אלתית","משמוש","הלאות","המולות","יקיא","מלואים","אלמותיות","שומים","אימותיהם","אימהיות","מהתלת","תושאל","מקמי","אוים","היקשו","השקיתי","לושה","תהלום","מושתלות","איומיהם","משקשקת","משאלו","מלתי","שתקי","תשקם","תוש","אקלקל","יאים","תלאותיהם","השא","שתלת","מולק","מימשת","משוי","מואשמות","משאלותיה","השתקמו","קמלה","ימקמו","מיואשות","קמלו","שמלותיה","תושאלו","משולות","קשקשתי","מלואה","תלאה","תקשקש","מלואו","מקשקשות","השתקתי","מושקי","מומיו","מלמלות","תשתול","משולמי","ימולו","תלאי","שקתות","מקלקלות","קיומים","תהמי","תלאים","תשתיק","אותיותיה","האשמותיה","השתלמותו","תשה","מקימו","אשמש","תושה","אקיא","האשמית","לאים","שמלתו","התשת","יהמו","הלומה","מושאה","מהלה","תיקל","קלקלתי","מהלו","שתיקתי","אשום","המותה","ויולות","יתלוש","משקמות","תיתלה","קשו","שתולות","שמלותיו","שקיה","האלהת","תושת","תשושות","תימלא","הלאימו","השתהיתי","אשוש","היתלות","מושו","משאה","משתיהם","ימיתו","תקלקלו","שולות","קימום","קתה","שקשק","יושתלו","תשתיתו","הלמי","תשתקם","אוימה","משות","שאלם","תשתיתה","יאושו","תשתיותיה","אוימו","אימותי","ימו","תשתק","אימותים","תשתלו","אשתול","השתקמות","התקלת","מושאו","הלקאות","התלהם","ותיקת","שמיו","קיאקי","השתלתו","מושאלות","מושתות","תשתיתיות","יושתל","משקיהם","ימשמש","תיקם","תקימי","יושתק","משתיקת","השקי","יקשקש","מקיאות","קלקלתו","יתושה","התלה","מלמלת","שתויות","אשק","השתיתו","תשאלה","תשתיותיו","משתיתה","קשקשה","איותיה","לאומיה","תושם","יקיאו","מושקית","לאומו","תהיותיו","יושאלו","מושתים","אולמותיו","השתיתה","מלאימה","משותקי","אלתי","שולקים","מושמות","תושתל","תלתול","ימלמל","תשותק","יתשאל","מותקי","שקשקתי","הלומות","השמשתי","שקיהם","תיאומו","תלאו","אלומותיו","אוית","תקתקתי","תושאלה","תלמו","איותים","אלתו","מושאיו","מקמה","תשהי","מלקי","מהמהמים","משתיתים","שותלות","יתויק","קמלות","שמשתה","התלהמויות","מולקי","אותיותיהם","אשמי","היאות","השתות","מושאיה","מקלותיהם","קשם","יקשקשו","שולק","תימול","אואשם","השהיתי","התלהמו","יתומיו","יהלו","יתושאל","שתומי","היתלה","התקלתי","התקשויות","משתלמי","המהמה","השאות","מיקשו","משושות","קלותה","השתקתו","ימלמלו","תקיאי","תשושת","יהמה","התשתי","תקשקשו","התקשותו","יאושם","משקמי","האשמותיהם","השתקתה","שקיו","תלולת","המיות","קלקלות","שושם","תקיאו","התלו","התקלקלתי","מלאימים","מלקת","מיקש","קלתה","תשאולו","איושה","ימשו","משתקמות","אקשקש","מקלת","משתקמי","לאומיותה","תשואותיהם","שתותי","השהית","התקלקלות","יאושה","יותש","מלקם","קשתותיו","שמשתו","שתיות","שמשותיו","השתלתה","שאולת","שקלם","תואשמו","תושתק","אשקם","יקמול","תשאלתי","השהי","יקמלו","תשות","אימיה","קלותו","מומיהם","קיאי","תשומותיו","השתה","מהלת","אשתיק","האלהתו","הימלאי","מושאות","היתלו","יקלה","אימותו","יהתלו","משמשה","שולו","תשקי","התקל","הלאיתי","הלמים","מולקים","הלאי","השתלמותה","היתקלותו","המהמו","יאוים","מהלתי","מושהת","מושתי","תולת","אולמים","איושו","הלקיתי","לאותי","שמלותיהם","תלושו","יתומיה","משושת","תלמיה","משותי","יאשו","ימשה","יתשאלו","שקמי","שתלם","תותו","תשתיקי","אולמותיה","אומותיהם","יותשו","ימהל","איותה","השתלתי","השתקמותו","התלהמה","יהתל","תהיותיה","תושתי","תיאותו","אלתה","השמשתו","יתושאלו","משקיו","תהמה","אויתה","איושם","מהלומותיו","מקשאות","אימותה","אשתק","הימול","התקשותה","יהלומיו","מושאיהם","קימומה","קלותי","תקתקת","תשתיותיהם","יתלהם","תיתלו","אלומותיהם","היאלמות","מקימיהם","משקיה","שמיהם","תולקי","אימותיה","הלאית","התלהמותו","יהלומיה","מקשתו","שומותיו","שתיתה","תשקמו","איתותיו","אלתיתי","המולתו","המומי","קשתותיהם","תיקלו","אשמותיו","לקיות","משויה","משתקי","תהתל","תיאותי","תשואותיו","תשקמי","אולמיה","היקלו","השתלמותי","התקלקלת","יתומו","מהמהמות","משקת","שמשותיהם","תלקי","יושמש","ימהלו","משתיתות","קימומו","תימק","אויתו","איותי","היאותה","היאשם","ויולת","יאוימו","לאומיותי","לולם","מולקת","מלאיו","מלאיות","משמשם","משתיו","תקמול","אולמיו","השתקמותה","מותקל","שמשותיה","תהיותיהם","תלתלה","תשומותיה","תשקשק","אויתי","אושם","השתיקי","יתלהמו","משקאותיה","שולקת","שומיו","תותיה","תלושת","תשתלמו","אומותיו","אימותיו","אשתקם","יתומיהם","משושו","משקאותיהם","משקלותיו","שהיותיו","תיאלם","תקלתי","תשאלת","תשואותיה","השתהית","מושמש","משולת","קיומיה","קשותי","איותו","השאלותיו","מלאימות","משאותיו","משתו","שומותיהם","תלאימו","איתותו","אשתלם","הימלא","היתקלותה","המותי","התשתו","יושמשו","יתושו","מלמולו","משאיותיה","משאיותיהם","משתקשק","משתקשקים","קמול","קתו","שותקתי","תימלאו","תשתהי","אולמותיהם","אלותיהם","היתלותו","היתלת","הלקי","התשות","ותקי","יושא","ימותיו","ימשמשו","מיקשת","מלמולה","משאיותיו","משמשתי","משקאותיו","קמלתי","קשתותיה","שומותיה","שקיקת","שתותיהם","תהמהם","תקתקי","אהמה","אושת","הלמותו","המולתה","מהלומותיה","קלקלתה","קשתיו","שתוית","שתותו","תושא","תושאלתי","תשומותיהם","איאות","אלמותו","הלקתה","השתיקם","התשתה","לקיקת","משהת","שקיותיו","שקיקתו","שקשקי","שתומה","תהלו","תימהל","תשאולם","היתקלו","היתקלויותיו","יושאו","מהתלותיו","מיתותיהם","משושם","קלושת","קלקלותיה","שולקי","שקיותיה","שקלולו","שתומים","תהתלו","תומיה","תיתום","תלמיו","תקלותיה","תקלתו","תשתקמו","אימיו","איתותיהם","אלתיות","אשתות","אשתל","האשמיות","היתלותה","הלמויות","המותו","השאלתה","יהמהמו","לאומיו","מקשתי","משקשקי","משתקשקת","קיומיו","שקיתי","שתותיה","תהלמו","תואשמי","תושו","תותש","תלתלו","תשאולה","תשולמי","אומותיה","אושתק","איתותיה","אשתית","היאלמותו","היתקל","המולתי","השמשתה","התלהמויותיו","יהמהם","ימקשו","מהלומותיהם","מלמולם","מקשו","משאיתה","משקלותיהם","קשותה","שקיקיו","שתולת","תושהי","תלתלת","תקלותיו","אהתל","אושק","איותיו","אימול","אשקשק","האלהתה","היאלמי","הימלאו","הלמיה","הלקית","השתלמויותיהם","התלהמותה","התקלתה","ימקש","מושות","מושמשת","מיתותיו","מלואיו","מלמלם","מקיאי","מקימותיה","מקלותיו","משאותיהם","קלקלותיהם","תהלמי","תהמו","תיאלמו","תיקלה","תקלותיהם","תשתות","תשתקמי","אולמיהם","אומיהם","אומיו","איתותה","אלומותיה","אלותיו","אשמותיהם","האהלתי","היאלמותה","הימולו","הימק","היתלתי","היתקלותי","השתלמויותיה","השתלמויותיו","השתקשק","התקלקלותו","התקשותי","ימותיה","יתלתל","מותקלת","מותקם","מקשתה","משמושה","משמושו","משמימי","קימומים","קלקלותיו","קמלת","קשתיה","קשתיתי","שומשמים","שקלולה","שקשקת","שתומות","שתיותיו","שתקם","תושמש","תיאומה","תימולו","תיקיותיה","תיקלתי","תיתש","תקתקם","תשאלם","תשקשקי","תשתלמי","אהלום","אותש","אלמותה","אשולם","האהלת","היאלם","הימהלות","הימלאה","הלאימי","המיותיו","השתלמי","השתקשקתי","יאויתו","יהלומו","לולאותיו","לושם","מהתלותיהם","מואשמי","מולקית","מושמשות","מושתקי","מימיותיהם","מיקשתי","מקימותיהם","מקימותיו","משויות","משושתי","קלקלם","קשתותי","קשתיהם","שותקי","שקיקתי","שתותה","שתותיו","תהמהמו","תהמהמי","תושמו","תושתו","תותקל","תותשו","תימלאי","תימשו","תיקלת","תלותיותה","תלתלתי","תקלתה","תקמלו","תשושו","אהמהם","אושאל","אימיהם","אשותק","אשמותיה","האלהתי","היאותו","היאלמה","היאלמו","היאשמה","היאשמי","היקלה","הלאותה","הלמיו","הלקאותיה","הלקאותיהם","המולותיו","המיותיה","השאותיו","השמותיהם","השקיותיו","התלהמותי","התקלקלויות","התקלקלותה","יאוית","יהלומיהם","ימושמשו","ימותיהם","יתומותיו","יתלתלו","מהתלתו","מהתלתי","מומשת","מושהי","מותקלות","מיתותיה","מלואיהם","מקשם","משאיתי","משאלם","משואותיה","משואותיהם","משואותיו","משוית","משושותיו","משותה","משותו","משמושם","משתהי","משתלותיהם","משתלותיו","משתלתה","משתלתו","משתלתי","קיאקיה","קיאקם","קיומיהם","קימותיו","קשקשם","קשתותו","קשתיותיה","קשתיותיו","קשתיתה","שהיותיה","שואותיהם","שואותיו","שומיה","שקיותיהם","שקיקתה","שקיתה","שקיתו","שקתותיהם","תויקתי","תולתל","תומיו","תושאלת","תותיו","תותקלו","תיאומיהם","תלאימי","תלותיותו","תלתולה","תלתלם"]}